moriarty/__init__.py
moriarty/core.py
moriarty/encryption.py
moriarty/forensic.py
moriarty/proxy_chain.py
moriarty/traffic_morph.py
moriart_python-0.2.dist-info/METADATA
moriart_python-0.2.dist-info/WHEEL
moriart_python-0.2.dist-info/entry_points.txt
moriart_python-0.2.dist-info/top_level.txt
moriart_python-0.2.dist-info/RECORD
