Metadata-Version: 2.4
Name: moriart_python
Version: 0.2
Summary: Advanced Traffic Obfuscation and Encryption Library
Author: Moriarty Security Team
Author-email: contact@moriarty.net
License: Apache 2.0
Keywords: security encryption anonymity networking privacy
Classifier: Development Status :: 4 - Beta
Classifier: Intended Audience :: Developers
Classifier: Topic :: Security :: Cryptography
Classifier: License :: OSI Approved :: Apache Software License
Classifier: Programming Language :: Python :: 3.8
Classifier: Programming Language :: Python :: 3.9
Classifier: Programming Language :: Python :: 3.10
Classifier: Programming Language :: Python :: 3.11
Classifier: Programming Language :: Python :: 3.12
Requires-Dist: cryptography>=42.0.0
Requires-Dist: pywin32>=306; platform_system == "Windows"
Dynamic: author
Dynamic: author-email
Dynamic: classifier
Dynamic: description
Dynamic: description-content-type
Dynamic: keywords
Dynamic: license
Dynamic: requires-dist
Dynamic: summary
